{ "backgroundcolor":"#abe1ff",
 "compressionlevel":-1,
 "height":20,
 "infinite":false,
 "layers":[
        {
         "data":[0, 0, 0, 0, 0, 0, 0, 0, 12, 12, 12, 0, 0, 0, 0, 0, 0, 4, 4, 4, 4, 0, 0, 0, 0, 0, 0, 0, 0, 0, 0, 0, 0, 0, 0, 0, 0, 0, 0, 0, 0, 0, 0, 0, 0, 0, 0, 0, 0, 0, 0, 0, 0, 0, 0, 0, 0, 0, 0, 0, 0, 0, 0, 0, 0, 0, 0, 0, 0, 0, 0, 0, 12, 12, 12, 0, 0, 0, 0, 0, 4, 0, 0, 0, 0, 4, 0, 0, 0, 0, 0, 0, 0, 0, 0, 0, 0, 0, 0, 0, 0, 0, 0, 0, 0, 0, 0, 0, 0, 0, 0, 0, 0, 0, 0, 0, 0, 0, 0, 0, 0, 0, 0, 0, 0, 0, 0, 0, 0, 0, 0, 0, 0, 0, 0, 0, 0, 0, 0, 0, 0, 0, 0, 4, 0, 0, 0, 0, 0, 0, 4, 0, 0, 0, 0, 0, 0, 0, 0, 0, 0, 0, 0, 0, 0, 0, 0, 0, 0, 0, 0, 0, 0, 0, 0, 0, 0, 0, 0, 0, 0, 0, 0, 0, 0, 0, 0, 0, 0, 0, 0, 0, 0, 0, 0, 0, 0, 0, 0, 0, 12, 12, 12, 0, 0, 0, 0, 0, 0, 0, 0, 0, 0, 0, 0, 0, 0, 0, 0, 0, 0, 0, 0, 0, 0, 0, 0, 0, 0, 0, 0, 0, 0, 0, 0, 0, 0, 0, 0, 0, 0, 0, 0, 0, 0, 0, 0, 0, 0, 0, 0, 0, 0, 0, 0, 0, 0, 0, 0, 0, 0, 12, 12, 12, 12, 12, 12, 12, 12, 12, 12, 0, 0, 0, 0, 0, 0, 0, 0, 12, 0, 0, 0, 0, 0, 0, 0, 0, 0, 0, 0, 0, 0, 0, 0, 0, 0, 0, 0, 0, 0, 0, 0, 0, 0, 0, 0, 0, 0, 0, 0, 0, 0, 0, 0, 0, 0, 0, 0, 0, 0, 0, 0, 12, 0, 0, 0, 0, 0, 0, 0, 0, 0, 0, 0, 0, 0, 0, 0, 0, 0, 0, 0, 0, 0, 0, 0, 0, 0, 0, 0, 0, 0, 0, 0, 0, 0, 0, 0, 0, 0, 0, 0, 0, 0, 0, 0, 0, 0, 0, 0, 0, 0, 0, 0, 0, 0, 0, 0, 0, 0, 0, 0, 0, 0, 0, 0, 12, 0, 0, 0, 0, 0, 0, 0, 0, 0, 0, 0, 0, 0, 0, 0, 0, 0, 0, 0, 0, 0, 0, 0, 0, 0, 0, 0, 0, 0, 0, 0, 0, 0, 0, 0, 0, 0, 0, 0, 0, 0, 0, 0, 0, 0, 0, 0, 0, 0, 0, 0, 0, 0, 0, 0, 0, 0, 0, 0, 0, 0, 0, 0, 12, 0, 0, 0, 0, 0, 0, 0, 0, 0, 0, 0, 0, 0, 0, 0, 0, 0, 0, 0, 0, 0, 0, 0, 0, 0, 0, 0, 0, 0, 0, 0, 0, 0, 0, 0, 0, 0, 0, 0, 0, 0, 0, 0, 0, 0, 0, 0, 0, 0, 0, 0, 0, 0, 0, 0, 0, 0, 0, 0, 0, 0, 0, 0, 12, 12, 12, 12, 12, 12, 12, 12, 12, 12, 12, 12, 12, 12, 12, 12, 12, 12, 12, 12, 12, 0, 0, 0, 0, 0, 0, 0, 0, 0, 0, 0, 0, 0, 0, 0, 0, 0, 0, 0, 0, 0, 0, 0, 0, 0, 0, 0, 0, 0, 0, 0, 0, 0, 0, 0, 0, 0, 0, 0, 0, 0, 0, 0, 0, 0, 0, 0, 0, 0, 0, 0, 0, 0, 0, 0, 0, 0, 0, 0, 0, 0, 0, 0, 0, 0, 0, 0, 0, 0, 0, 0, 0, 0, 0, 0, 0, 0, 0, 0, 0, 0, 0, 0, 0, 0, 0, 0, 0, 0, 0, 0, 0, 0, 0, 0, 0, 0, 0, 0, 0, 0, 0, 0, 0, 0, 0, 0, 0, 0, 0, 0, 0, 0, 0, 0, 0, 0, 0, 0, 0, 0, 0, 0, 0, 0, 0, 0, 0, 0, 0, 12, 12, 7, 7, 7, 12, 0, 0, 0, 0, 0, 0, 0, 0, 0, 0, 0, 0, 0, 0, 0, 0, 0, 0, 0, 0, 0, 0, 0, 0, 0, 0, 0, 0, 0, 0, 0, 0, 0, 0, 0, 0, 0, 0, 0, 0, 0, 0, 0, 0, 0, 0, 0, 0, 0, 0, 0, 0, 0, 0, 0, 0, 0, 0, 0, 12, 0, 0, 0, 12, 0, 0, 0, 0, 0, 0, 0, 0, 0, 0, 0, 0, 0, 0, 0, 0, 0, 0, 0, 0, 0, 0, 0, 0, 0, 0, 0, 0, 0, 0, 0, 0, 0, 0, 0, 0, 0, 0, 0, 0, 0, 0, 0, 0, 0, 0, 0, 0, 0, 0, 0, 0, 0, 0, 12, 12, 12, 0, 0, 12, 7, 7, 7, 12, 0, 0, 0, 0, 0, 0, 0, 0, 0, 0, 9, 2684354569, 7, 7, 7, 7, 9, 2684354569, 0, 0, 0, 0, 9, 2684354569, 0, 0, 0, 0, 0, 0, 0, 0, 0, 0, 0, 0, 0, 0, 0, 0, 0, 0, 0, 0, 0, 0, 0, 0, 0, 0, 0, 0, 0, 0, 0, 0, 0, 0, 0, 12, 0, 0, 0, 12, 0, 0, 0, 0, 0, 0, 0, 0, 0, 0, 1610612744, 2684354568, 0, 0, 0, 0, 1610612744, 2684354568, 0, 0, 0, 0, 1610612744, 2684354568, 0, 0, 0, 0, 0, 0, 1, 0, 0, 0, 0, 0, 0, 0, 0, 0, 0, 0, 0, 0, 0, 0, 0, 0, 0, 0, 12, 12, 12, 0, 0, 0, 0, 0, 0, 12, 0, 0, 0, 12, 0, 0, 0, 0, 0, 0, 0, 0, 0, 1, 1610612744, 2684354568, 7, 7, 7, 7, 1610612744, 2684354568, 0, 0, 0, 0, 1610612744, 2684354568, 0, 0, 0, 0, 0, 0, 9, 8, 0, 0, 0, 0, 0, 0, 0, 0, 0, 0, 0, 0, 0, 0, 0, 0, 0, 0, 0, 0, 0, 0, 0, 0, 0, 0, 0, 12, 7, 7, 7, 12, 0, 0, 0, 0, 0, 0, 0, 0, 9, 8, 10, 2684354568, 0, 0, 0, 0, 1610612744, 2684354568, 0, 0, 0, 0, 1610612744, 2684354568, 0, 0, 0, 0, 0, 0, 1610612744, 11, 0, 0, 0, 0, 0, 0, 0, 0, 0, 0, 0, 0, 0, 0, 12, 12, 12, 0, 0, 0, 0, 0, 0, 0, 0, 0, 0, 0, 0, 0, 0, 0, 0, 0, 0, 1, 0, 0, 0, 0, 1610612745, 3221225480, 3221225480, 3221225481, 0, 12, 12, 0, 1610612744, 2684354568, 0, 0, 0, 0, 1610612744, 2684354568, 0, 1, 0, 0, 0, 0, 1610612744, 11, 0, 0, 0, 0, 0, 0, 0, 0, 0, 0, 1, 0, 0, 0, 0, 0, 0, 0, 0, 0, 0, 0, 0, 0, 1, 0, 9, 8, 8, 8, 8, 8, 8, 8, 8, 8, 8, 2684354569, 0, 0, 0, 0, 0, 0, 0, 0, 0, 0, 1610612744, 2684354568, 0, 0, 0, 0, 1610612744, 2684354570, 8, 8, 8, 8, 8, 8, 10, 11, 0, 0, 0, 0, 1, 0, 0, 0, 9, 8, 8, 2684354569, 0, 0, 0, 0, 0, 0, 0, 1, 0, 0, 9, 8, 8, 8, 10, 11, 11, 11, 11, 11, 11, 11, 11, 11, 11, 2684354568, 0, 0, 0, 0, 0, 0, 0, 0, 0, 0, 1610612744, 2684354568, 0, 0, 0, 0, 1610612744, 11, 11, 11, 11, 11, 11, 11, 11, 11, 8, 8, 8, 8, 8, 2684354569, 0, 0, 1610612744, 11, 11, 2684354570, 8, 8, 8, 8, 8, 8, 8, 8, 8, 8, 10, 11, 11, 11, 11, 11, 11, 11, 11, 11, 11, 11, 11, 11, 11, 2684354570, 8, 8, 8, 8, 8, 8, 8, 8, 8, 8, 10, 2684354568, 0, 0, 0, 0, 1610612744, 11, 11, 11, 11, 11, 11, 11, 11, 11],
         "height":20,
         "id":1,
         "name":"Tiles",
         "opacity":1,
         "type":"tilelayer",
         "visible":true,
         "width":64,
         "x":0,
         "y":0
        }, 
        {
         "draworder":"topdown",
         "id":2,
         "name":"Enemies",
         "objects":[
                {
                 "gid":17,
                 "height":16,
                 "id":12,
                 "name":"",
                 "rotation":0,
                 "type":"",
                 "visible":true,
                 "width":16,
                 "x":32,
                 "y":152
                }, 
                {
                 "gid":17,
                 "height":16,
                 "id":13,
                 "name":"",
                 "rotation":0,
                 "type":"",
                 "visible":true,
                 "width":16,
                 "x":152,
                 "y":152
                }, 
                {
                 "gid":17,
                 "height":16,
                 "id":14,
                 "name":"",
                 "rotation":0,
                 "type":"",
                 "visible":true,
                 "width":16,
                 "x":224,
                 "y":80
                }, 
                {
                 "gid":17,
                 "height":16,
                 "id":15,
                 "name":"",
                 "rotation":0,
                 "type":"",
                 "visible":true,
                 "width":16,
                 "x":112,
                 "y":64
                }, 
                {
                 "gid":17,
                 "height":16,
                 "id":16,
                 "name":"",
                 "rotation":0,
                 "type":"",
                 "visible":true,
                 "width":16,
                 "x":472,
                 "y":136
                }],
         "opacity":1,
         "type":"objectgroup",
         "visible":true,
         "x":0,
         "y":0
        }],
 "nextlayerid":3,
 "nextobjectid":17,
 "orientation":"orthogonal",
 "renderorder":"right-down",
 "tiledversion":"2021.03.23",
 "tileheight":8,
 "tilesets":[
        {
         "firstgid":1,
         "source":"tiles.json"
        }, 
        {
         "firstgid":17,
         "source":"object_tilesets\/renky.json"
        }],
 "tilewidth":8,
 "type":"map",
 "version":1.5,
 "width":64
}